{"LocalizedTexts":[{"ID":"play","AltID":"Play","Value":"Αναπαραγωγή"},{"ID":"delete","AltID":"Delete","Value":"Διαγραφή"},{"ID":"off","AltID":"Off","Value":"Απενεργοποίηση"},{"ID":"on","AltID":"On","Value":"Ενεργοποίηση"},{"ID":"continue","AltID":"Continue","Value":"Συνέχεια"},{"ID":"settings","AltID":"Settings","Value":"Ρυθμίσεις"},{"ID":"seatedmode","AltID":"Seated mode","Value":"Καθιστή λειτουργία"},{"ID":"deletesaveddata","AltID":"Delete saved data","Value":"Διαγραφή αποθηκευμένων δεδομένων"},{"ID":"thisisahandtrackingandcontrollerexperience","AltID":"This is a hand-tracking and controller experience","Value":"Αυτή είναι μια εμπειρία που περιλαμβάνει παρακολούθηση χεριών και χειριστήρια"},{"ID":"pleasefollowtheguidelinesbelow","AltID":"Please follow the guidelines below","Value":"Ακολούθησε τις παρακάτω οδηγίες"},{"ID":"playinawelllitspace","AltID":"Play in a well-lit space","Value":"Παίξε σε χώρο με καλό φωτισμό"},{"ID":"highcontrastbetweenhandsandbackground","AltID":"High contrast between hands and background","Value":"Υψηλή αντίθεση μεταξύ χεριών και φόντου"},{"ID":"keepcontrollerswithinreachabledistance","AltID":"Keep controllers within reachable distance","Value":"Φρόντισε τα χειριστήρια να βρίσκονται σε προσβάσιμη απόσταση"},{"ID":"optionforplayingtheexperiencesittingdown","AltID":"Option for playing the experience sitting down","Value":"Επιλογή παιχνιδιού σε καθιστή θέση"},{"ID":"dontshowthisagain","AltID":"Don't show this again","Value":"Να μην εμφανιστεί ξανά"},{"ID":"thiswontappearagainuntilthesavedataiscleared","AltID":"This won't appear again until the save data is cleared","Value":"Δεν θα εμφανιστεί ξανά μέχρι να διαγραφούν τα δεδομένα αποθήκευσης"},{"ID":"sceneunderstanding","AltID":"Scene Understanding","Value":"Κατανόηση σκηνής"},{"ID":"thisexperienceisenhancedwithsceneunderstandingduringroomsetupcontrollersmayberequired","AltID":"This experience is enhanced with Scene Understanding. During room setup controllers may be required.","Value":"Η εμπειρία βελτιώνεται με την κατανόηση σκηνής. Κατά τη διαμόρφωση δωματίου ενδέχεται να χρειαστούν χειριστήρια"},{"ID":"pause","AltID":"Pause","Value":"Παύση"},{"ID":"resume","AltID":"Resume","Value":"Συνέχιση"},{"ID":"settings","AltID":"Settings","Value":"Ρυθμίσεις"},{"ID":"help","AltID":"Help","Value":"Βοήθεια"},{"ID":"mainmenu","AltID":"Main menu","Value":"Κύριο μενού"},{"ID":"hub","AltID":"Hub","Value":"Κέντρο"},{"ID":"restartlevel","AltID":"Restart level","Value":"Επανεκκίνηση επιπέδου"},{"ID":"howtoteleport","AltID":"How to teleport","Value":"Πώς να τηλεμεταφερθώ"},{"ID":"howtosnapturn","AltID":"How to snap-turn","Value":"Πώς να στρίψω με ένα κλικ"},{"ID":"hint","AltID":"Hint","Value":"Συμβουλή"},{"ID":"howtouseportal","AltID":"How to use portal","Value":"Πώς να χρησιμοποιήσω την πύλη"},{"ID":"howtousemap","AltID":"How to use map","Value":"Πώς να χρησιμοποιήσω τον χάρτη"},{"ID":"howtousevoicesdk","AltID":"How to use Voice SDK","Value":"Πώς να χρησιμοποιήσω το SDK φωνητικών εντολών"},{"ID":"howtoinstalltheadapters","AltID":"How to install the adapters","Value":"Πώς να εγκαταστήσω τους προσαρμογείς"},{"ID":"howtousethecontrollers","AltID":"How to use the controllers","Value":"Πώς να χρησιμοποιήσω τα χειριστήρια"},{"ID":"distancegrab","AltID":"Distance grab","Value":"Πιάσιμο αντικειμένου από απόσταση"},{"ID":"dronebattle","AltID":"Drone battle","Value":"Μάχη με drone"},{"ID":"openyourhand","AltID":"Open your hand","Value":"Άνοιξε το χέρι σου"},{"ID":"pointtowardsadirection","AltID":"Point towards a direction","Value":"Δείξε προς μια κατεύθυνση"},{"ID":"pinchtoselect","AltID":"Pinch to select","Value":"Τσίμπησε για να επιλέξεις"},{"ID":"holdyourhandsidewaysandpreparetopinch","AltID":"Hold your hand sideways and prepare to pinch","Value":"Κράτησε το χέρι σου στο πλάι και ετοιμάσου να τσιμπήσεις"},{"ID":"moveyourhand","AltID":"Move your hand","Value":"Κούνησε το χέρι σου"},{"ID":"movethecontrollertotheadapterconnectionport","AltID":"Move the controller to the adapter connection port","Value":"Μετακίνησε το χειριστήριο στη θύρα σύνδεσης προσαρμογέα"},{"ID":"holdthegriptriggertoaffixtheadapter","AltID":"Hold the grip trigger to affix the adapter","Value":"Πάτησε παρατεταμένα το κουμπί ενεργοποίησης λαβής για να στερεώσεις τον προσαρμογέα"},{"ID":"aimatanobjectafterinstallingtheadapter","AltID":"Aim at an object after installing the adapter","Value":"Στόχευσε ένα αντικείμενο μετά την τοποθέτηση του προσαρμογέα"},{"ID":"holdtheindexfingertriggertoselect","AltID":"Hold the index finger trigger to select","Value":"Πάτησε παρατεταμένα το κουμπί ενεργοποίησης δείκτη για να επιλέξεις"},{"ID":"interactwithobjects","AltID":"Interact with objects","Value":"Αλληλεπίδρασε με αντικείμενα"},{"ID":"findobjectsintheportal","AltID":"Find objects in the portal","Value":"Βρες αντικείμενα στην πύλη"},{"ID":"putyourhandintotheportalandtakeouttheobject","AltID":"Put your hand into the portal and take out the object","Value":"Βάλε το χέρι σου μέσα στην πύλη και βγάλε το αντικείμενο"},{"ID":"clickondifferenthotspots","AltID":"Click on different hotspots","Value":"Κάνε κλικ σε διαφορετικά hotspot"},{"ID":"theportalsopendifferentscenes","AltID":"The portals open different scenes","Value":"Οι πύλες ανοίγουν διαφορετικές σκηνές"},{"ID":"speakthecommandsyouneedthedronetodo","AltID":"Speak the commands you need the drone to do","Value":"Πες τις εντολές που θέλεις να εκτελέσει το drone"},{"ID":"thedronewillrecieveyourcommandsandtakeaction","AltID":"The Drone will recieve your commands and take action","Value":"Το drone θα λάβει τις εντολές σου και θα αναλάβει δράση"},{"ID":"openyourhandandaimatanobject","AltID":"Open your hand and aim at an object","Value":"Άνοιξε το χέρι σου και στόχευσε ένα αντικείμενο"},{"ID":"closeyourhandtograbtheobjectremotely","AltID":"Close your hand to grab the object remotely","Value":"Κλείσε το χέρι σου για να πιάσεις το αντικείμενο από απόσταση"},{"ID":"palmblast","AltID":"Palm Blast","Value":"Έκρηξη με την παλάμη"},{"ID":"defence","AltID":"Defence","Value":"Άμυνα"},{"ID":"nointernetconnection","AltID":"No Internet Connection","Value":"Δεν υπάρχει σύνδεση στο διαδίκτυο"},{"ID":"voicesdk","AltID":"VOICE SDK","Value":"SDK ΦΩΝΗΤΙΚΩΝ ΕΝΤΟΛΩΝ"},{"ID":"iftheresnointernetconnectionyouwontbeabletousethevoicesdkmeaningyoullhavetousebuttonsinstead","AltID":"If there's no internet connection, you won't be able to use the voice SDK, meaning you'll have to use buttons instead.","Value":"Εάν δεν υπάρχει σύνδεση στο διαδίκτυο, δεν μπορεί να χρησιμοποιηθεί το SDK φωνητικών εντολών. Αυτό σημαίνει ότι θα πρέπει να χρησιμοποιηθούν τα κουμπιά"},{"ID":"voicecommandsarenotavailablerightnow","AltID":"Voice commands are not available right now","Value":"Οι φωνητικές εντολές δεν είναι διαθέσιμες αυτή τη στιγμή"},{"ID":"voicecommandsarenotavailablewithoutinternet","AltID":"Voice commands are not available without internet","Value":"Οι φωνητικές εντολές δεν είναι διαθέσιμες χωρίς σύνδεση στο διαδίκτυο"},{"ID":"voicecommandsarenotavailablewithoutmicrophonepermissions","AltID":"Voice commands are not available without microphone permissions","Value":"Οι φωνητικές εντολές δεν είναι διαθέσιμες χωρίς δικαιώματα χρήσης μικροφώνου"},{"ID":"buttonscanbeusedevenwhenvoicecommandsarenotavailable","AltID":"Buttons can be used even when voice commands are not available","Value":"Τα κουμπιά μπορούν να χρησιμοποιηθούν ακόμη και όταν οι φωνητικές εντολές δεν είναι διαθέσιμες"},{"ID":"controllersneeded","AltID":"Controllers needed","Value":"Απαιτούνται χειριστήρια"},{"ID":"thisexperienceisbestwithcontrollerspleasepickupyourcontrollersnowtocontinue","AltID":"This experience is best with controllers, please pick up your controllers now to continue","Value":"Αυτή η εμπειρία είναι καλύτερη με χειριστήρια. Διάλεξε τώρα τα χειριστήριά σου για να συνεχίσεις"},{"ID":"controllersbeingdetected","AltID":"Controllers being detected...","Value":"Εντοπισμός χειριστηρίων"},{"ID":"nothanksilikehandtracking","AltID":"No thanks, I like hand tracking","Value":"Όχι, ευχαριστώ. Προτιμώ την παρακολούθηση χεριών"},{"ID":"althoughthisisacontrollersexperience","AltID":"Although this is a controllers experience","Value":"Παρόλο που αυτή είναι μια εμπειρία με χειριστήρια"},{"ID":"creator","AltID":"Creator","Value":"Δημιουργός"},{"ID":"verifying","AltID":"Verifying...","Value":"Επαλήθευση"},{"ID":"powerglove","AltID":"Power glove","Value":"Γάντι χειρισμού"},{"ID":"locomotion","AltID":"Locomotion","Value":"Κίνηση"},{"ID":"voicemodule","AltID":"Voice module","Value":"Μονάδα φωνητικών εντολών"},{"ID":"controllers","AltID":"Controllers","Value":"Χειριστήρια"},{"ID":"disabled","AltID":"Disabled","Value":"Απενεργοποιήθηκε"},{"ID":"verified","AltID":"Verified","Value":"Επαληθεύτηκε"},{"ID":"placetheorb","AltID":"Place the orb","Value":"Τοποθέτησε τη σφαίρα"},{"ID":"explore","AltID":"Explore","Value":"Εξερεύνηση"},{"ID":"hints","AltID":"Hints","Value":"Συμβουλές"},{"ID":"handtracking","AltID":"Hand tracking","Value":"Παρακολούθηση χεριών"},{"ID":"usehandtrackingforthebestexperience","AltID":"Use hand tracking for the best experience","Value":"Χρησιμοποίησε παρακολούθηση χεριών για τη βέλτιστη εμπειρία"},{"ID":"controllers","AltID":"Controllers","Value":"Χειριστήρια"},{"ID":"usecontrollersforthebestexperience","AltID":"Use controllers for the best experience","Value":"Χρησιμοποίησε χειριστήρια για τη βέλτιστη εμπειρία"},{"ID":"skip","AltID":"Skip","Value":"Παράλειψη"},{"ID":"clocktower","AltID":"Clock Tower","Value":"Πύργος ρολογιού"},{"ID":"thegenerator","AltID":"The Generator","Value":"Η γεννήτρια"},{"ID":"thetown","AltID":"The Town","Value":"Η πόλη"},{"ID":"mountainpeak","AltID":"Mountain Peak","Value":"Κορυφή βουνού"},{"ID":"town","AltID":"Town","Value":"Πόλη"},{"ID":"generator","AltID":"Generator","Value":"Γεννήτρια"},{"ID":"mountains","AltID":"Mountains","Value":"Βουνά"},{"ID":"locked","AltID":"Locked","Value":"Κλειδωμένο"},{"ID":"enabled","AltID":"Enabled","Value":"Ενεργοποιημένο"},{"ID":"replay","AltID":"Replay","Value":"Επανάληψη"},{"ID":"haptics","AltID":"Haptics","Value":"Κιναισθητική"},{"ID":"youcompletedfirsthand","AltID":"You Completed First Hand!","Value":"Ολοκληρώσατε το First Hand!"},{"ID":"experiencemoregreatcontentonthemetaqueststore","AltID":"Experience more great content on the Meta Quest Store","Value":"Απολαύστε ακόμα περισσότερο εκπληκτικό περιεχόμενο στο Meta Quest Store"},{"ID":"store","AltID":"Store","Value":"Store"},{"ID":"coinsfound","AltID":"Coins Found","Value":"Βρέθηκαν νομίσματα"},{"ID":"snapturn","AltID":"Snap turn","Value":"Στροφή με ένα κλικ"},{"ID":"teleport","AltID":"Teleport","Value":"Τηλεμεταφορά"},{"ID":"howtoturnholdyourhandsidewaysanddothepointgesture","AltID":"How to turn. Hold your hand sideways and do the point gesture.","Value":"Πώς να στρίψω. Κράτησε το χέρι σου στο πλάι και κάνε τη χειρονομία κατάδειξης"},{"ID":"howtoteleportpointtowardsadirectionandpinchtoselect","AltID":"How to teleport. Point towards a direction and pinch to select.","Value":"Πώς να τηλεμεταφερθώ. Δείξε προς μια κατεύθυνση και τσίμπησε για να επιλέξεις"},{"ID":"howtoteleportextendyourindexfingerandcurltheothersthenpinch","AltID":"How to teleport. Extend your index finger and curl the others, then pinch.","Value":"Πώς να τηλεμεταφερθώ. Τεντώστε το δείκτη σας και κυρτώστε τα άλλα δάχτυλα, στη συνέχεια «τσιμπήστε»"},{"ID":"howtoturnleftmoveyourhandtotheleftandpinchtoselect","AltID":"How to turn left. Move your hand to the left and pinch to select.","Value":"Πώς να στρίψω αριστερά. Μετακίνησε το χέρι σου προς τα αριστερά και τσίμπησε για να επιλέξεις"},{"ID":"howtoturnrightmoveyourhandtotherightandpinchtoselect","AltID":"How to turn right. Move your hand to the right and pinch to select.","Value":"Πώς να στρίψω δεξιά. Μετακίνησε το χέρι σου προς τα δεξιά και τσίμπησε για να επιλέξεις"},{"ID":"attention","AltID":"Attention","Value":"Προσοχή"},{"ID":"upgrade","AltID":"Upgrade","Value":"Αναβάθμιση"},{"ID":"successawesomeyouaregoodtogo","AltID":"Success! Awesome! You are good to go...","Value":"Συγχαρητήρια! Εξαιρετικά! Έτοιμοι να ξεκινήσουμε"},{"ID":"successyesnowonemoretime","AltID":"Success! Yes! Now one more time!","Value":"Συγχαρητήρια! Ναι! Μία ακόμα φορά!"},{"ID":"successgreatdoitagain","AltID":"Success! Great! Do it again...","Value":"Συγχαρητήρια! Τέλεια! Κάν’ το ξανά"},{"ID":"successawesomeletsgiveitatwist","AltID":"Success! Awesome! Let's give it a twist.","Value":"Συγχαρητήρια! Εξαιρετικά! Ας δοκιμάσουμε κάπως αλλιώς"},{"ID":"successgreatletsturntotheleft","AltID":"Success! Great! Let's turn to the left!","Value":"Συγχαρητήρια! Τέλεια! Ας στρίψουμε αριστερά!"},{"ID":"successgreatletsturntotheright","AltID":"Success! Great! Let's turn to the right!","Value":"Συγχαρητήρια! Τέλεια! Ας στρίψουμε δεξιά!"},{"ID":"howtoteleportmovethejoystickforwardandreleasetoteleport","AltID":"How to teleport. Move the joystick forward and release to teleport.","Value":"Τρόπος τηλεμεταφοράς. Μετακινήστε το joystick προς τα εμπρός και αφήστε το για τηλεμεταφορά"},{"ID":"howtoturnleftmovethejoysticktothelefttoturnleft","AltID":"How to turn left. Move the joystick to the left to turn left.","Value":"Πώς να στρίψετε αριστερά. Μετακινήστε το joystick προς τα αριστερά για να στρίψετε αριστερά"},{"ID":"howtoturnrightmovethejoysticktotherighttoturnright","AltID":"How to turn right. Move the joystick to the right to turn right.","Value":"Πώς να στρίψετε δεξιά. Μετακινήστε το joystick προς τα δεξιά για να στρίψετε δεξιά"},{"ID":"codeaccepted","AltID":"Code Accepted","Value":"Αποδεκτός κωδικός"},{"ID":"invalidcode","AltID":"Invalid Code","Value":"Μη έγκυρος κωδικός"},{"ID":"entercode","AltID":"Enter Code","Value":"Εισαγωγή κωδικού"},{"ID":"closeenough","AltID":"Close Enough","Value":"Close Enough"},{"ID":"cancelbattle","AltID":"Cancel Battle","Value":"Ακύρωση μάχης"},{"ID":"fusebox","AltID":"Fuse box","Value":"Κιβώτιο ασφαλειών"},{"ID":"box","AltID":"Box","Value":"Κιβώτιο"},{"ID":"brokenfuse","AltID":"Broken fuse","Value":"Καμμένη ασφάλεια"},{"ID":"fuse","AltID":"Fuse","Value":"Ασφάλεια"},{"ID":"generator1","AltID":"Generator 1","Value":"Γεννήτρια 1"},{"ID":"generator2","AltID":"Generator 2","Value":"Γεννήτρια 2"},{"ID":"illheadtothegeneratorwecanworkasateam","AltID":"I'll head to the generator, we can work as a team","Value":"Θα πάω στη γεννήτρια, μπορούμε να δουλέψουμε σαν ομάδα"},{"ID":"oncebothgeneratorsarefunctionalpulltheleverandpushthebuttontopowerupthemachineryabove","AltID":"Once both generators are functional, pull the lever and push the button to power up the machinery above","Value":"Μόλις λειτουργήσουν και οι δύο γεννήτριες, τράβηξε τον μοχλό και πάτησε το κουμπί για να ενεργοποιηθούν τα μηχανήματα από πάνω"},{"ID":"atgenerator2afuseneedsreplacing","AltID":"At generator 2 a fuse needs replacing","Value":"Στη γεννήτρια 2 μια ασφάλεια πρέπει να αντικατασταθεί"},{"ID":"atgenerator1itlookslikesomethingsobstructingtheblades","AltID":"At generator 1 it looks like somethings obstructing the blades","Value":"Στη γεννήτρια 1 φαίνεται ότι κάτι εμποδίζει τα πτερύγια"},{"ID":"topowerupthemachineryaboveusweneedtogetthesegeneratorsupandrunning","AltID":"To power up the machinery above us we need to get these generators up and running","Value":"Για να ενεργοποιηθούν τα μηχανήματα που βρίσκονται από πάνω μας πρέπει να θέσουμε σε λειτουργία αυτές τις γεννήτριες"},{"ID":"sayacommandtomeandiwillrespondandactonit","AltID":"Say a command to me and I will respond and act on it","Value":"Πες μου μια εντολή και θα την εκτελέσω"},{"ID":"hello","AltID":"\"Hello\"","Value":"\"Γεια\""},{"ID":"lookaround","AltID":"\"Look Around\"","Value":"\"Ρίξε μια ματιά\""},{"ID":"flytothegenerator","AltID":"\"Fly to the generator\"","Value":"\"Πέταξε προς τη γεννήτρια\""},{"ID":"theworkbench","AltID":"The Workbench","Value":"Ο πάγκος εργασίας"},{"ID":"theshelved","AltID":"The Shelved","Value":"Τα ράφια"},{"ID":"theconveyor","AltID":"The Conveyor","Value":"Ο μεταφορέας"},{"ID":"thestash","AltID":"The Stash","Value":"Η κρύπτη"},{"ID":"thebridge","AltID":"The Bridge","Value":"Η γέφυρα"},{"ID":"thetunnels","AltID":"The Tunnels","Value":"Οι σήραγγες"},{"ID":"theconsole","AltID":"The Console","Value":"Η κονσόλα"},{"ID":"thestoreroom","AltID":"The Store Room","Value":"Η αποθήκη"},{"ID":"theexplorer","AltID":"The Explorer","Value":"Ο εξερευνητής"},{"ID":"theshortcircuit","AltID":"The Short Circuit","Value":"Το βραχυκύκλωμα"},{"ID":"theblockage","AltID":"The Blockage","Value":"Το μπλοκάρισμα"},{"ID":"theprisoner","AltID":"The Prisoner","Value":"Ο φυλακισμένος"},{"ID":"theclocktower","AltID":"The Clock Tower","Value":"Ο πύργος ρολογιού"},{"ID":"theshopper","AltID":"The Shopper","Value":"Ο αγοραστής"},{"ID":"thebargainhunter","AltID":"The Bargain Hunter","Value":"Ο κυνηγός ευκαιριών"},{"ID":"themechanic","AltID":"The Mechanic","Value":"Ο μηχανικός"},{"ID":"thesentinel","AltID":"The Sentinel","Value":"Ο φρουρός"},{"ID":"theplatformer","AltID":"The Platformer","Value":"Η πλατφόρμα"},{"ID":"thehighflyer","AltID":"The High Flyer","Value":"Ο επιτυχημένος"},{"ID":"thecollector","AltID":"The Collector","Value":"Ο συλλέκτης"},{"ID":"thevoyager","AltID":"The Voyager","Value":"Ο ταξιδιώτης"},{"ID":"thetracker","AltID":"The Tracker","Value":"Ο ιχνηλάτης"},{"ID":"thepainter","AltID":"The Painter","Value":"Ο ζωγράφος"},{"ID":"thewingman","AltID":"The Wingman","Value":"Ο πτέρυγας"},{"ID":"theeasytarget","AltID":"The Easy Target","Value":"Ο εύκολος στόχος"},{"ID":"thesleeper","AltID":"The Sleeper","Value":"Ο κρεβάτι"}]}